{
    "package": "lodash.merge",
    "version": "4.6.0",
    "dep_nums": 110,
    "dependents": [
        {
            "no": 1,
            "package": "@commitlint/resolve-extends",
            "version": "5.2.8",
            "dep_nums": 1,
            "dependents": [
                {
                    "no": 1,
                    "package": "@commitlint/core",
                    "version": "5.2.8"
                }
            ]
        },
        {
            "no": 2,
            "package": "heroku-cli-addons",
            "version": "1.2.26",
            "dep_nums": 10,
            "dependents": [
                {
                    "no": 1,
                    "package": "heroku-pg",
                    "version": "2.9.0"
                },
                {
                    "no": 2,
                    "package": "heroku-fork",
                    "version": "4.1.22"
                },
                {
                    "no": 3,
                    "package": "@hyperoslo/heroku-pg-filter",
                    "version": "1.0.0"
                },
                {
                    "no": 4,
                    "package": "heroku-cli",
                    "version": "6.14.41"
                },
                {
                    "no": 5,
                    "package": "fwc-heroku-fork",
                    "version": "4.1.29"
                },
                {
                    "no": 6,
                    "package": "heroku-fork-fin",
                    "version": "4.1.28"
                },
                {
                    "no": 7,
                    "package": "@heroku/heroku-cli-dev-center-generator",
                    "version": "1.1.8"
                },
                {
                    "no": 8,
                    "package": "heroku-pg-filter",
                    "version": "1.0.0"
                },
                {
                    "no": 9,
                    "package": "skilljar-heroku-fork",
                    "version": "4.1.27"
                },
                {
                    "no": 10,
                    "package": "@heroku-cli/plugin-pg",
                    "version": "2.9.0"
                }
            ]
        },
        {
            "no": 3,
            "package": "@commitlint/core",
            "version": "5.2.8",
            "dep_nums": 2,
            "dependents": [
                {
                    "no": 1,
                    "package": "@commitlint/cli",
                    "version": "5.2.8"
                },
                {
                    "no": 2,
                    "package": "@commitlint/prompt",
                    "version": "5.2.8"
                }
            ]
        },
        {
            "no": 4,
            "package": "ut-port-jsonrpc",
            "version": "5.6.12",
            "dep_nums": 5,
            "dependents": [
                {
                    "no": 1,
                    "package": "ut-port-registry",
                    "version": "0.2.0"
                },
                {
                    "no": 2,
                    "package": "@mojaloop/dfsp-transfer",
                    "version": "0.20.24"
                },
                {
                    "no": 3,
                    "package": "@mojaloop/dfsp-ussd",
                    "version": "1.0.0"
                },
                {
                    "no": 4,
                    "package": "@mojaloop/dfsp-identity",
                    "version": "0.10.6"
                },
                {
                    "no": 5,
                    "package": "@mojaloop/dfsp-api",
                    "version": "1.0.0"
                }
            ]
        },
        {
            "no": 5,
            "package": "ut-port-httpserver",
            "version": "8.11.7",
            "dep_nums": 9,
            "dependents": [
                {
                    "no": 1,
                    "package": "@mojaloop/dfsp-api",
                    "version": "1.0.0"
                },
                {
                    "no": 2,
                    "package": "@mojaloop/dfsp-directory",
                    "version": "0.7.29"
                },
                {
                    "no": 3,
                    "package": "@mojaloop/dfsp-identity",
                    "version": "0.10.6"
                },
                {
                    "no": 4,
                    "package": "@mojaloop/dfsp-ledger",
                    "version": "2.0.0"
                },
                {
                    "no": 5,
                    "package": "@mojaloop/dfsp-rule",
                    "version": "0.5.26"
                },
                {
                    "no": 6,
                    "package": "@mojaloop/dfsp-subscription",
                    "version": "0.5.11"
                },
                {
                    "no": 7,
                    "package": "@mojaloop/dfsp-transfer",
                    "version": "0.20.24"
                },
                {
                    "no": 8,
                    "package": "@mojaloop/dfsp-ussd",
                    "version": "1.0.0"
                },
                {
                    "no": 9,
                    "package": "@mojaloop/dfsp-account",
                    "version": "0.9.28"
                }
            ]
        },
        {
            "no": 6,
            "package": "ut-run",
            "version": "8.4.2",
            "dep_nums": 9,
            "dependents": [
                {
                    "no": 1,
                    "package": "@mojaloop/dfsp-api",
                    "version": "1.0.0"
                },
                {
                    "no": 2,
                    "package": "@mojaloop/dfsp-directory",
                    "version": "0.7.29"
                },
                {
                    "no": 3,
                    "package": "@mojaloop/dfsp-identity",
                    "version": "0.10.6"
                },
                {
                    "no": 4,
                    "package": "@mojaloop/dfsp-ledger",
                    "version": "2.0.0"
                },
                {
                    "no": 5,
                    "package": "@mojaloop/dfsp-rule",
                    "version": "0.5.26"
                },
                {
                    "no": 6,
                    "package": "@mojaloop/dfsp-subscription",
                    "version": "0.5.11"
                },
                {
                    "no": 7,
                    "package": "@mojaloop/dfsp-transfer",
                    "version": "0.20.24"
                },
                {
                    "no": 8,
                    "package": "@mojaloop/dfsp-ussd",
                    "version": "1.0.0"
                },
                {
                    "no": 9,
                    "package": "@mojaloop/dfsp-account",
                    "version": "0.9.28"
                }
            ]
        },
        {
            "no": 7,
            "package": "@commitlint/cli",
            "version": "5.2.8",
            "dep_nums": 6,
            "dependents": [
                {
                    "no": 1,
                    "package": "commitlint",
                    "version": "5.2.8"
                },
                {
                    "no": 2,
                    "package": "@commitlint/travis-cli",
                    "version": "5.2.8"
                },
                {
                    "no": 3,
                    "package": "@southfarm/es-dev-tools",
                    "version": "0.3.2"
                },
                {
                    "no": 4,
                    "package": "arui-presets",
                    "version": "4.10.1"
                },
                {
                    "no": 5,
                    "package": "ybiq",
                    "version": "1.0.0"
                },
                {
                    "no": 6,
                    "package": "@makeomatic/deploy",
                    "version": "5.0.0"
                }
            ]
        },
        {
            "no": 8,
            "package": "react-native-simple-store",
            "version": "1.3.0",
            "dep_nums": 8,
            "dependents": [
                {
                    "no": 1,
                    "package": "backbone-cache-react-native",
                    "version": "0.0.2"
                },
                {
                    "no": 2,
                    "package": "backbone-offline-react-native",
                    "version": "0.0.1"
                },
                {
                    "no": 3,
                    "package": "eostoken",
                    "version": "0.0.1"
                },
                {
                    "no": 4,
                    "package": "lastmile-ui-mapbox",
                    "version": "0.0.2"
                },
                {
                    "no": 5,
                    "package": "react-native-http-datacache",
                    "version": "1.0.0"
                },
                {
                    "no": 6,
                    "package": "react-native-s3",
                    "version": "0.0.10"
                },
                {
                    "no": 7,
                    "package": "uc-rn-v2-shared",
                    "version": "1.0.0"
                },
                {
                    "no": 8,
                    "package": "@eransch/react-native-s3",
                    "version": "0.0.22"
                }
            ]
        },
        {
            "no": 9,
            "package": "express-minify-html",
            "version": "0.12.0",
            "dep_nums": 6,
            "dependents": [
                {
                    "no": 1,
                    "package": "fusing-angular",
                    "version": "0.0.0"
                },
                {
                    "no": 2,
                    "package": "maf-cli",
                    "version": "1.5.10"
                },
                {
                    "no": 3,
                    "package": "make-it-easy",
                    "version": "0.0.1"
                },
                {
                    "no": 4,
                    "package": "nv-node-project",
                    "version": "1.0.0"
                },
                {
                    "no": 5,
                    "package": "roosevelt",
                    "version": "0.11.0"
                },
                {
                    "no": 6,
                    "package": "@produle/prevjs",
                    "version": "0.0.3"
                }
            ]
        },
        {
            "no": 10,
            "package": "cli-engine-command",
            "version": "4.0.3",
            "dep_nums": 2,
            "dependents": [
                {
                    "no": 1,
                    "package": "cli-engine-heroku",
                    "version": "0.3.1"
                },
                {
                    "no": 2,
                    "package": "cli-engine",
                    "version": "3.3.6"
                }
            ]
        },
        {
            "no": 11,
            "package": "cli-engine-heroku",
            "version": "0.3.2",
            "dep_nums": 4,
            "dependents": [
                {
                    "no": 1,
                    "package": "heroku-apps",
                    "version": "2.3.1"
                },
                {
                    "no": 2,
                    "package": "heroku-orgs",
                    "version": "1.6.2"
                },
                {
                    "no": 3,
                    "package": "heroku-spaces",
                    "version": "2.9.2"
                },
                {
                    "no": 4,
                    "package": "cli-engine",
                    "version": "3.3.8"
                }
            ]
        },
        {
            "no": 12,
            "package": "typeable",
            "version": "0.21.0",
            "dep_nums": 3,
            "dependents": [
                {
                    "no": 1,
                    "package": "validatable",
                    "version": "0.22.0"
                },
                {
                    "no": 2,
                    "package": "objectschema",
                    "version": "3.10.0"
                },
                {
                    "no": 3,
                    "package": "contextable",
                    "version": "3.2.1"
                }
            ]
        },
        {
            "no": 13,
            "package": "amperize",
            "version": "0.3.4",
            "dep_nums": 4,
            "dependents": [
                {
                    "no": 1,
                    "package": "ghost",
                    "version": "0.11.10"
                },
                {
                    "no": 2,
                    "package": "gulp-amperify",
                    "version": "1.1.1"
                },
                {
                    "no": 3,
                    "package": "morganatwork-ghost",
                    "version": "1.1.0"
                },
                {
                    "no": 4,
                    "package": "@morgs32/ghost",
                    "version": "1.5.0"
                }
            ]
        },
        {
            "no": 14,
            "package": "browsertime",
            "version": "1.0.0-beta.10",
            "dep_nums": 2,
            "dependents": [
                {
                    "no": 1,
                    "package": "webcoach",
                    "version": "0.29.0"
                },
                {
                    "no": 2,
                    "package": "sitespeed.io",
                    "version": "4.0.5"
                }
            ]
        },
        {
            "no": 15,
            "package": "trails",
            "version": "3.2.2",
            "dep_nums": 4,
            "dependents": [
                {
                    "no": 1,
                    "package": "generator-trailpack",
                    "version": "0.0.2"
                },
                {
                    "no": 2,
                    "package": "generator-trails",
                    "version": "0.0.10"
                },
                {
                    "no": 3,
                    "package": "generator-treefrog",
                    "version": "1.0.0-alpha-1"
                },
                {
                    "no": 4,
                    "package": "generator-hapi-micro",
                    "version": "1.0.0"
                }
            ]
        },
        {
            "no": 16,
            "package": "materialize-react",
            "version": "0.2.0-alpha.20",
            "dep_nums": 1,
            "dependents": [
                {
                    "no": 1,
                    "package": "@tf2-pickup/config",
                    "version": "0.6.0"
                }
            ]
        },
        {
            "no": 17,
            "package": "handleable",
            "version": "0.17.0",
            "dep_nums": 1,
            "dependents": [
                {
                    "no": 1,
                    "package": "contextable",
                    "version": "3.2.1"
                }
            ]
        },
        {
            "no": 18,
            "package": "webcoach",
            "version": "0.29.0",
            "dep_nums": 1,
            "dependents": [
                {
                    "no": 1,
                    "package": "sitespeed.io",
                    "version": "4.0.7"
                }
            ]
        },
        {
            "no": 19,
            "package": "sitespeed.io",
            "version": "4.0.7",
            "dep_nums": 2,
            "dependents": [
                {
                    "no": 1,
                    "package": "gulp-sitespeedio",
                    "version": "1.0.0"
                },
                {
                    "no": 2,
                    "package": "grunt-sitespeedio",
                    "version": "1.0.2"
                }
            ]
        },
        {
            "no": 20,
            "package": "ut-front-react",
            "version": "9.12.6",
            "dep_nums": 2,
            "dependents": [
                {
                    "no": 1,
                    "package": "@mojaloop/dfsp-rule",
                    "version": "0.5.26"
                },
                {
                    "no": 2,
                    "package": "@mojaloop/dfsp-admin",
                    "version": "0.17.44"
                }
            ]
        },
        {
            "no": 21,
            "package": "kyt",
            "version": "0.9.0",
            "dep_nums": 1,
            "dependents": [
                {
                    "no": 1,
                    "package": "druid-kyt-default-configuration",
                    "version": "0.1.0-alpha.fb5d4fb"
                }
            ]
        },
        {
            "no": 22,
            "package": "ut-port-http",
            "version": "7.3.0",
            "dep_nums": 2,
            "dependents": [
                {
                    "no": 1,
                    "package": "ut-service",
                    "version": "0.1.2"
                },
                {
                    "no": 2,
                    "package": "ut-port-jsonrpc",
                    "version": "6.0.0"
                }
            ]
        },
        {
            "no": 23,
            "package": "kinvey-cli",
            "version": "4.1.1",
            "dep_nums": 1,
            "dependents": [
                {
                    "no": 1,
                    "package": "kinvey-cli-wrapper",
                    "version": "0.0.2"
                }
            ]
        },
        {
            "no": 24,
            "package": "ut-port-script",
            "version": "6.0.0",
            "dep_nums": 2,
            "dependents": [
                {
                    "no": 1,
                    "package": "ut-port-amqp",
                    "version": "0.4.5"
                },
                {
                    "no": 2,
                    "package": "ut-service",
                    "version": "0.10.0"
                }
            ]
        },
        {
            "no": 25,
            "package": "ut-rule",
            "version": "5.8.22",
            "dep_nums": 2,
            "dependents": [
                {
                    "no": 1,
                    "package": "@mojaloop/dfsp-rule",
                    "version": "0.5.26"
                },
                {
                    "no": 2,
                    "package": "@mojaloop/dfsp-admin",
                    "version": "0.17.44"
                }
            ]
        },
        {
            "no": 26,
            "package": "@times-components/author-profile",
            "version": "0.10.0",
            "dep_nums": 1,
            "dependents": [
                {
                    "no": 1,
                    "package": "@times-components/provider",
                    "version": "0.7.0"
                }
            ]
        },
        {
            "no": 27,
            "package": "@tf2-pickup/components",
            "version": "0.3.0",
            "dep_nums": 1,
            "dependents": [
                {
                    "no": 1,
                    "package": "@tf2-pickup/icons",
                    "version": "1.0.0"
                }
            ]
        },
        {
            "no": 28,
            "package": "@digitaslbiparis/webcoach",
            "version": "1.1.2",
            "dep_nums": 1,
            "dependents": [
                {
                    "no": 1,
                    "package": "@digitaslbiparis/sitespeed.io",
                    "version": "6.2.6"
                }
            ]
        },
        {
            "no": 29,
            "package": "frack-core",
            "version": "0.1.0",
            "dep_nums": 1,
            "dependents": [
                {
                    "no": 1,
                    "package": "frack-kit-universal-redux",
                    "version": "0.1.1"
                }
            ]
        },
        {
            "no": 30,
            "package": "augur-node",
            "version": "0.2.5",
            "dep_nums": 1,
            "dependents": [
                {
                    "no": 1,
                    "package": "augur-app",
                    "version": "1.0.3"
                }
            ]
        },
        {
            "no": 31,
            "package": "@commitlint/config-patternplate",
            "version": "5.2.7",
            "dep_nums": 1,
            "dependents": [
                {
                    "no": 1,
                    "package": "commitlint-config-patternplate",
                    "version": "5.0.0"
                }
            ]
        },
        {
            "no": 32,
            "package": "ut-port-sql",
            "version": "7.4.0",
            "dep_nums": 1,
            "dependents": [
                {
                    "no": 1,
                    "package": "ut-service",
                    "version": "0.10.0"
                }
            ]
        },
        {
            "no": 33,
            "package": "ut-ussd",
            "version": "6.8.0",
            "dep_nums": 1,
            "dependents": [
                {
                    "no": 1,
                    "package": "@mojaloop/dfsp-ussd",
                    "version": "1.0.0"
                }
            ]
        },
        {
            "no": 34,
            "package": "js-gardener",
            "version": "1.5.2",
            "dep_nums": 1,
            "dependents": [
                {
                    "no": 1,
                    "package": "lambda-tdd",
                    "version": "1.0.0"
                }
            ]
        },
        {
            "no": 35,
            "package": "aor-simple-graphql-client",
            "version": "0.0.1",
            "dep_nums": 0,
            "dependents": []
        },
        {
            "no": 36,
            "package": "lambundaler",
            "version": "0.10.0",
            "dep_nums": 0,
            "dependents": []
        },
        {
            "no": 37,
            "package": "@lab009/app-config",
            "version": "2.0.0",
            "dep_nums": 0,
            "dependents": []
        },
        {
            "no": 38,
            "package": "abacus-user-preferences-client",
            "version": "1.0.1",
            "dep_nums": 0,
            "dependents": []
        },
        {
            "no": 39,
            "package": "kinase",
            "version": "0.1.0",
            "dep_nums": 0,
            "dependents": []
        },
        {
            "no": 40,
            "package": "abacus-instrumentation-client",
            "version": "1.0.0",
            "dep_nums": 0,
            "dependents": []
        },
        {
            "no": 41,
            "package": "@heroku-cli/plugin-addons",
            "version": "1.2.26",
            "dep_nums": 0,
            "dependents": []
        },
        {
            "no": 42,
            "package": "@uphold/uphold-sdk-javascript",
            "version": "1.0.0",
            "dep_nums": 0,
            "dependents": []
        },
        {
            "no": 43,
            "package": "insta-api-node",
            "version": "0.0.1",
            "dep_nums": 0,
            "dependents": []
        },
        {
            "no": 44,
            "package": "@haiku/player",
            "version": "2.0.100",
            "dep_nums": 0,
            "dependents": []
        },
        {
            "no": 45,
            "package": "ins-model",
            "version": "0.0.1",
            "dep_nums": 0,
            "dependents": []
        },
        {
            "no": 46,
            "package": "ut-port-mail",
            "version": "7.0.0",
            "dep_nums": 0,
            "dependents": []
        },
        {
            "no": 47,
            "package": "hyper-broadcast",
            "version": "1.0.0",
            "dep_nums": 0,
            "dependents": []
        },
        {
            "no": 48,
            "package": "@rtobon/rumba",
            "version": "1.5.4",
            "dep_nums": 0,
            "dependents": []
        },
        {
            "no": 49,
            "package": "@guumaster/rpgen",
            "version": "0.0.4",
            "dep_nums": 0,
            "dependents": []
        },
        {
            "no": 50,
            "package": "insilico-tasks",
            "version": "1.0.1",
            "dep_nums": 0,
            "dependents": []
        },
        {
            "no": 51,
            "package": "@deskproapps/deskproapps-sdk-react",
            "version": "1.0.0-alpha.10",
            "dep_nums": 0,
            "dependents": []
        },
        {
            "no": 52,
            "package": "jira-rest-client",
            "version": "1.0.0",
            "dep_nums": 0,
            "dependents": []
        },
        {
            "no": 53,
            "package": "jrbotros-test-tent",
            "version": "0.1.10",
            "dep_nums": 0,
            "dependents": []
        },
        {
            "no": 54,
            "package": "ut-port-file",
            "version": "6.0.0",
            "dep_nums": 0,
            "dependents": []
        },
        {
            "no": 55,
            "package": "haiku.ai",
            "version": "2.0.10",
            "dep_nums": 0,
            "dependents": []
        },
        {
            "no": 56,
            "package": "@rtobon/app-config",
            "version": "1.3.1",
            "dep_nums": 0,
            "dependents": []
        },
        {
            "no": 57,
            "package": "koa-app-base",
            "version": "1.0.0",
            "dep_nums": 0,
            "dependents": []
        },
        {
            "no": 58,
            "package": "gulp-sitespeedio",
            "version": "1.0.0",
            "dep_nums": 0,
            "dependents": []
        },
        {
            "no": 59,
            "package": "grunt-sitespeedio",
            "version": "1.0.0",
            "dep_nums": 0,
            "dependents": []
        },
        {
            "no": 60,
            "package": "mad-spring-connect",
            "version": "0.0.1",
            "dep_nums": 0,
            "dependents": []
        },
        {
            "no": 61,
            "package": "@ricardo-tobon/rumba",
            "version": "1.5.4",
            "dep_nums": 0,
            "dependents": []
        },
        {
            "no": 62,
            "package": "micromono",
            "version": "0.10.0",
            "dep_nums": 0,
            "dependents": []
        },
        {
            "no": 63,
            "package": "@graf009/app-config",
            "version": "1.3.0",
            "dep_nums": 0,
            "dependents": []
        },
        {
            "no": 64,
            "package": "grunt-gardener",
            "version": "1.0.0",
            "dep_nums": 0,
            "dependents": []
        },
        {
            "no": 65,
            "package": "ultraui",
            "version": "1.4.5",
            "dep_nums": 0,
            "dependents": []
        },
        {
            "no": 66,
            "package": "@ricardo-tobon/app-config",
            "version": "1.3.1",
            "dep_nums": 0,
            "dependents": []
        },
        {
            "no": 67,
            "package": "express-request-parameters",
            "version": "0.1.0",
            "dep_nums": 0,
            "dependents": []
        },
        {
            "no": 68,
            "package": "then-busboy",
            "version": "1.0.0",
            "dep_nums": 0,
            "dependents": []
        },
        {
            "no": 69,
            "package": "express-minify-html-terser",
            "version": "1.0.0",
            "dep_nums": 0,
            "dependents": []
        },
        {
            "no": 70,
            "package": "@nas-user/rumba",
            "version": "1.5.3",
            "dep_nums": 0,
            "dependents": []
        },
        {
            "no": 71,
            "package": "@fabrix/fabrix",
            "version": "1.0.0-alpha.1",
            "dep_nums": 0,
            "dependents": []
        },
        {
            "no": 72,
            "package": "tessellate-fragment",
            "version": "0.2.0",
            "dep_nums": 0,
            "dependents": []
        },
        {
            "no": 73,
            "package": "tarec",
            "version": "1.3.0",
            "dep_nums": 0,
            "dependents": []
        },
        {
            "no": 74,
            "package": "sitespeed.webscanner",
            "version": "5.3.4",
            "dep_nums": 0,
            "dependents": []
        },
        {
            "no": 75,
            "package": "ember-tachyons-sweeper",
            "version": "0.0.1",
            "dep_nums": 0,
            "dependents": []
        },
        {
            "no": 76,
            "package": "@nas-user/app-config",
            "version": "1.3.0",
            "dep_nums": 0,
            "dependents": []
        },
        {
            "no": 77,
            "package": "sitespeed",
            "version": "4.3.4",
            "dep_nums": 0,
            "dependents": []
        },
        {
            "no": 78,
            "package": "tf2pickup-components",
            "version": "0.2.0",
            "dep_nums": 0,
            "dependents": []
        },
        {
            "no": 79,
            "package": "shrimpit",
            "version": "0.1.0",
            "dep_nums": 0,
            "dependents": []
        },
        {
            "no": 80,
            "package": "rf-db-settings",
            "version": "0.0.2",
            "dep_nums": 0,
            "dependents": []
        },
        {
            "no": 81,
            "package": "config-man",
            "version": "0.1.3",
            "dep_nums": 0,
            "dependents": []
        },
        {
            "no": 82,
            "package": "typeconf",
            "version": "0.4.0",
            "dep_nums": 0,
            "dependents": []
        },
        {
            "no": 83,
            "package": "@namgoe/gcmsgen",
            "version": "0.0.11",
            "dep_nums": 0,
            "dependents": []
        },
        {
            "no": 84,
            "package": "uni-config",
            "version": "0.0.1",
            "dep_nums": 0,
            "dependents": []
        },
        {
            "no": 85,
            "package": "ut-codec",
            "version": "5.10.0",
            "dep_nums": 0,
            "dependents": []
        },
        {
            "no": 86,
            "package": "ut-codec-iso8583",
            "version": "6.1.0",
            "dep_nums": 0,
            "dependents": []
        },
        {
            "no": 87,
            "package": "ut-codec-ndc",
            "version": "6.1.0",
            "dep_nums": 0,
            "dependents": []
        },
        {
            "no": 88,
            "package": "ut-codec-payshield",
            "version": "6.1.0",
            "dep_nums": 0,
            "dependents": []
        },
        {
            "no": 89,
            "package": "react-native-xsy-store",
            "version": "0.0.1",
            "dep_nums": 0,
            "dependents": []
        },
        {
            "no": 90,
            "package": "ut-port",
            "version": "6.0.1",
            "dep_nums": 0,
            "dependents": []
        },
        {
            "no": 91,
            "package": "ut-port-amqp",
            "version": "0.4.4",
            "dep_nums": 0,
            "dependents": []
        },
        {
            "no": 92,
            "package": "ut-port-console",
            "version": "6.3.0",
            "dep_nums": 0,
            "dependents": []
        },
        {
            "no": 93,
            "package": "progressive-web-sdk",
            "version": "0.15.5",
            "dep_nums": 0,
            "dependents": []
        },
        {
            "no": 94,
            "package": "patternplate-legacy-defaults",
            "version": "1.2.0",
            "dep_nums": 0,
            "dependents": []
        },
        {
            "no": 95,
            "package": "buzzphrase",
            "version": "2.4.0",
            "dep_nums": 0,
            "dependents": []
        },
        {
            "no": 96,
            "package": "@n8mellis/kyt",
            "version": "0.5.4",
            "dep_nums": 0,
            "dependents": []
        },
        {
            "no": 97,
            "package": "parasprite",
            "version": "1.0.0-beta.3",
            "dep_nums": 0,
            "dependents": []
        },
        {
            "no": 98,
            "package": "ut-port-schedule",
            "version": "6.0.0",
            "dep_nums": 0,
            "dependents": []
        },
        {
            "no": 99,
            "package": "outliner-loader",
            "version": "0.0.4",
            "dep_nums": 0,
            "dependents": []
        },
        {
            "no": 100,
            "package": "mtgnewsbot",
            "version": "1.0.2",
            "dep_nums": 0,
            "dependents": []
        }
    ]
}
